{
  "key": "VideoElement",
  "displayName": "Video",
  "description": "Add a video to an experience",
  "baseType": "_component",
  "sortOrder": 0,
  "mayContainTypes": [],
  "mediaFileExtensions": [],
  "compositionBehaviors": [
    "elementEnabled"
  ],
  "properties": {
    "video": {
      "type": "contentReference",
      "displayName": "Video",
      "description": "",
      "isLocalized": false,
      "isRequired": true,
      "group": "Content",
      "sortOrder": 10,
      "allowedTypes": [
        "Video"
      ],
      "restrictedTypes": []
    },
    "title": {
      "type": "string",
      "format": "shortString",
      "displayName": "Title",
      "description": "Alternative text when video is unavailable",
      "isLocalized": true,
      "isRequired": false,
      "group": "Content",
      "sortOrder": 20
    },
    "placeholder": {
      "type": "contentReference",
      "displayName": "Placeholder",
      "description": "Placeholder to show before video is started",
      "isLocalized": false,
      "isRequired": false,
      "group": "Content",
      "sortOrder": 30,
      "allowedTypes": [
        "Image"
      ],
      "restrictedTypes": []
    }
  }
}
